loothelp/__init__.py
loothelp/app.py
loothelp/counter.py
loothelp/main.py
loothelp/overlay.py
loothelp-0.1.0.dist-info/METADATA
loothelp-0.1.0.dist-info/WHEEL
loothelp-0.1.0.dist-info/entry_points.txt
loothelp-0.1.0.dist-info/licenses/LICENSE
loothelp-0.1.0.dist-info/RECORD
