Metadata-Version: 2.4
Name: loothelp
Version: 0.1.0
Summary: A simple transparent loot tracking overlay.
Author: Me
License: MIT
License-File: LICENSE
Requires-Python: >=3.13
Requires-Dist: keyboard
Requires-Dist: pyqt6
